setup.py
twitter_of_babble/__init__.py
twitter_of_babble/database_connector.py
twitter_of_babble/tweet_janitor.py
twitter_of_babble.egg-info/PKG-INFO
twitter_of_babble.egg-info/SOURCES.txt
twitter_of_babble.egg-info/dependency_links.txt
twitter_of_babble.egg-info/not-zip-safe
twitter_of_babble.egg-info/top_level.txt