Metadata-Version: 1.0
Name: twitter-of-babble
Version: 0.1.41
Summary: Twitter Topic Models and Linguistic Diversity
Home-page: https://github.com/jcbain/twitter_of_babble
Author: James Bain
Author-email: jamescbain@gmail.com
License: UNKNOWN
Platform: UNKNOWN
